kaggle_data/__init__.py
kaggle_data/downloader.py
kaggle_data/utils.py
kaggle_data-0.4.dist-info/DESCRIPTION.rst
kaggle_data-0.4.dist-info/METADATA
kaggle_data-0.4.dist-info/RECORD
kaggle_data-0.4.dist-info/WHEEL
kaggle_data-0.4.dist-info/metadata.json
kaggle_data-0.4.dist-info/top_level.txt
