Metadata-Version: 2.0
Name: kaggle-data
Version: 0.4
Summary: An unofficial Kaggle datasets downloader
Home-page: https://github.com/EKami/kaggle_data
Author: GODARD Tuatini
Author-email: tuatinigodard@gmail.com
License: MIT
Keywords: development
Platform: UNKNOWN
Classifier: Development Status :: 3 - Alpha
Classifier: Intended Audience :: Developers
Classifier: Topic :: Software Development :: Build Tools
Classifier: License :: OSI Approved :: MIT License
Classifier: Programming Language :: Python :: 3
Classifier: Programming Language :: Python :: 3.3
Classifier: Programming Language :: Python :: 3.4
Classifier: Programming Language :: Python :: 3.5
Classifier: Programming Language :: Python :: 3.6
Requires-Dist: mechanicalsoup
Requires-Dist: progressbar2
